pymechanics/__init__.py
pymechanics/fluids/__init__.py
pymechanics/fluids/pressure.py
pymechanics/fluids/properties.py
pymechanics/fluids/surface.py
pymechanics/fluids/exercises/exercise_1_1.py
pymechanics/utils/__init__.py
pymechanics/utils/constants.py
pymechanics-0.2.0.dist-info/licenses/LICENSE
pymechanics-0.2.0.dist-info/METADATA
pymechanics-0.2.0.dist-info/WHEEL
pymechanics-0.2.0.dist-info/top_level.txt
pymechanics-0.2.0.dist-info/RECORD
