Metadata-Version: 2.4
Name: pymechanics
Version: 0.2.0
Summary: A Python library for classical mechanical engineering calculations
Author: Bakare Abdullateef Opeyemi
License: MIT
Project-URL: Homepage, https://github.com/bakare-opeyemi/pymechanics
Requires-Python: >=3.9
License-File: LICENSE
Requires-Dist: numpy
Requires-Dist: scipy
Dynamic: license-file
